antiCPy
